LICENSE.txt
README.md
setup.cfg
setup.py
Perdy/PrettyYAML.py
Perdy/__init__.py
Perdy/diff.py
Perdy/eddo.py
Perdy/parser.py
Perdy/pretty.py
Perdy/pyson.py
Perdy/pyxbext.py
Perdy.egg-info/PKG-INFO
Perdy.egg-info/SOURCES.txt
Perdy.egg-info/dependency_links.txt
Perdy.egg-info/requires.txt
Perdy.egg-info/top_level.txt
bin/colourize.py
bin/parser.py
bin/pyson.py