Metadata-Version: 2.2
Name: Perdy
Version: 1.14
Home-page: https://github.com/eddo888/perdy
Download-URL: https://github.com/eddo888/perdy/archive/1.14.tar.gz
Author: David Edson
Author-email: eddo888@tpg.com.au
License: MIT
License-File: LICENSE.txt
Requires-Dist: pytz
Requires-Dist: arrow
Requires-Dist: dotmap
Requires-Dist: xmltodict
Requires-Dist: PyYAML
Requires-Dist: jsonpath
Requires-Dist: argcomplete
Requires-Dist: Baubles
Dynamic: author
Dynamic: author-email
Dynamic: description
Dynamic: description-content-type
Dynamic: download-url
Dynamic: home-page
Dynamic: license
Dynamic: requires-dist
